<?xml version="1.0" encoding="UTF-8"?>
<lom:lom xmlns:lom="http://ltsc.ieee.org/xsd/LOM"><lom:educational><lom:description><lom:string language="en-US">N/A</lom:string></lom:description><lom:difficulty/><lom:intendedEndUserRole/><lom:interactivityLevel/><lom:interactivityType/><lom:learningResourceType/><lom:semanticDensity/><lom:language>en-US</lom:language></lom:educational><lom:general><lom:aggregationLevel><lom:source>LOMv1.0</lom:source><lom:value>2</lom:value></lom:aggregationLevel><lom:coverage><lom:string language="en-US">united-states</lom:string></lom:coverage><lom:description><lom:string language="en-US">This article published on DEBATE at Nature.com by Nature Publishing Group.  "Increasing attention has been drawn to the problems faced by women in science, engineering and technology (SET). Women are unequally represented in science and their career progression is not comparable to their male colleagues. The growing interest in this topic may partly be because of the growing awareness of the huge untapped economic potential that women represent."
keywords: gender equity</lom:string></lom:description><lom:identifier><lom:catalog>NEEDS</lom:catalog><lom:entry>B4878E0B-8535-4A7E-86A6-87E90B2E757B</lom:entry></lom:identifier><lom:keyword><lom:string language="en-US">Earthquakes, Seismic data, emergency response</lom:string></lom:keyword><lom:structure><lom:source>LOMv1.0</lom:source><lom:value>hierarchical</lom:value></lom:structure><lom:title><lom:string language="en-US">Why are there so few women in science?</lom:string></lom:title><lom:language>en-US</lom:language></lom:general><lom:lifeCycle><lom:contribute><lom:entity>BEGIN:VCARD
VERSION:3.0
SOURCE:http://www.smete.org
UID:7B4D6204-D1DF-4D1A-879F-1A698E2F599D
N:Nancy;Lane;null;;
FN:Lane Nancy
END:vCard</lom:entity><lom:role><lom:source>LOMv1.0</lom:source><lom:value>author</lom:value></lom:role><lom:date><lom:dateTime>1999-09-01</lom:dateTime></lom:date></lom:contribute><lom:version><lom:string language="en-US">N/A</lom:string></lom:version></lom:lifeCycle><lom:metaMetadata><lom:contribute><lom:entity>BEGIN:VCARD
VERSION:3.0
SOURCE:http://www.smete.org
UID:3BD3C8E5-C45A-41B5-9D62-CD6961AA4A5A
N:premier-award judge;;;;
FN:premier-award judge
END:vCard</lom:entity><lom:role><lom:source>LOMv1.0</lom:source><lom:value>creator</lom:value></lom:role><lom:date><lom:dateTime>2005-03-07</lom:dateTime></lom:date></lom:contribute><lom:identifier><lom:catalog>NEEDS</lom:catalog><lom:entry>B4878E0B-8535-4A7E-86A6-87E90B2E757B</lom:entry></lom:identifier><lom:language>en-US</lom:language><lom:metadataSchema>LOMv1.0</lom:metadataSchema></lom:metaMetadata><lom:rights><lom:copyrightAndOtherRestrictions><lom:source>LOMv1.0</lom:source><lom:value>yes</lom:value></lom:copyrightAndOtherRestrictions><lom:cost><lom:source>LOMv1.0</lom:source><lom:value>no</lom:value></lom:cost></lom:rights><lom:technical><lom:format/><lom:installationRemarks><lom:string language="en-US">N/A</lom:string></lom:installationRemarks><lom:location>http://www.nature.com/nature/debates/women/women_frameset.html</lom:location><lom:otherPlatformRequirements><lom:string language="en-US">N/A</lom:string></lom:otherPlatformRequirements><lom:size>0</lom:size></lom:technical></lom:lom>