<?xml version="1.0" encoding="UTF-8"?>
<lom:lom xmlns:lom="http://ltsc.ieee.org/xsd/LOM"><lom:educational><lom:description><lom:string language="en-US">N/A</lom:string></lom:description><lom:difficulty/><lom:intendedEndUserRole/><lom:interactivityLevel/><lom:interactivityType/><lom:learningResourceType/><lom:semanticDensity/><lom:language>en-US</lom:language></lom:educational><lom:general><lom:aggregationLevel><lom:source>LOMv1.0</lom:source><lom:value>2</lom:value></lom:aggregationLevel><lom:coverage><lom:string language="en-US">united-states</lom:string></lom:coverage><lom:description><lom:string language="en-US">Describes the process of starting a new program in computer science and engineering that is heavily based on applied mathematics and only open to women. Emphasizes that success requires considerable interest in mathematics and curiosity about computer science among female students at the secondary level and the acceptance of the single-sex program by the university.</lom:string></lom:description><lom:identifier><lom:catalog>NEEDS</lom:catalog><lom:entry>21F04CD3-4D86-4908-B62F-7110C3BF3DDB</lom:entry></lom:identifier><lom:keyword><lom:string language="en-US">all-female environment,,,</lom:string></lom:keyword><lom:structure><lom:source>LOMv1.0</lom:source><lom:value>hierarchical</lom:value></lom:structure><lom:title><lom:string language="en-US">Encouraging More Women Into Computer Science: Initiating a Single-Sex Intervention Program in Sweden</lom:string></lom:title><lom:language>en-US</lom:language></lom:general><lom:lifeCycle><lom:contribute><lom:entity>BEGIN:VCARD
VERSION:3.0
SOURCE:http://www.smete.org
UID:F7001484-DF90-4DCD-8389-E42E18921EAE
N:Brandell;Gerd;null;;
FN:Gerd Brandell
END:vCard</lom:entity><lom:role><lom:source>LOMv1.0</lom:source><lom:value>author</lom:value></lom:role><lom:date><lom:dateTime>1997-01-01</lom:dateTime></lom:date></lom:contribute><lom:contribute><lom:entity>BEGIN:VCARD
VERSION:3.0
SOURCE:http://www.smete.org
UID:E75AC75A-62C3-44AF-A85C-7449551B16F7
N:Carlsson;Svante;null;;
FN:Svante Carlsson
END:vCard</lom:entity><lom:role><lom:source>LOMv1.0</lom:source><lom:value>author</lom:value></lom:role><lom:date><lom:dateTime>1997-01-01</lom:dateTime></lom:date></lom:contribute><lom:contribute><lom:entity>BEGIN:VCARD
VERSION:3.0
SOURCE:http://www.smete.org
UID:88E595B1-3785-434C-8044-38639B678657
N:Elkbom;Hakan;null;;
FN:Hakan Elkbom
END:vCard</lom:entity><lom:role><lom:source>LOMv1.0</lom:source><lom:value>author</lom:value></lom:role><lom:date><lom:dateTime>1997-01-01</lom:dateTime></lom:date></lom:contribute><lom:contribute><lom:entity>BEGIN:VCARD
VERSION:3.0
SOURCE:http://www.smete.org
UID:572023F4-E083-410B-AC80-218DA5140532
N:Nord;Ann-Charlotte;null;;
FN:Ann-Charlotte Nord
END:vCard</lom:entity><lom:role><lom:source>LOMv1.0</lom:source><lom:value>author</lom:value></lom:role><lom:date><lom:dateTime>1997-01-01</lom:dateTime></lom:date></lom:contribute><lom:contribute><lom:entity>BEGIN:VCARD
VERSION:3.0
SOURCE:http://www.smete.org
UID:C620427B-9147-4830-8642-24723B3AFF61
N:c;;;;
FN:c
END:vCard</lom:entity><lom:role><lom:source>LOMv1.0</lom:source><lom:value>publisher</lom:value></lom:role><lom:date><lom:dateTime>1997-01-01</lom:dateTime></lom:date></lom:contribute><lom:version><lom:string language="en-US">N/A</lom:string></lom:version></lom:lifeCycle><lom:metaMetadata><lom:contribute><lom:entity>BEGIN:VCARD
VERSION:3.0
SOURCE:http://www.smete.org
UID:A44FA0BE-7A9E-4127-BB01-71C0DED343D9
N:ACM Women in Computing Editor;;;;
FN:ACM Women in Computing Editor
END:vCard</lom:entity><lom:role><lom:source>LOMv1.0</lom:source><lom:value>creator</lom:value></lom:role><lom:date><lom:dateTime>2005-04-01</lom:dateTime></lom:date></lom:contribute><lom:identifier><lom:catalog>NEEDS</lom:catalog><lom:entry>21F04CD3-4D86-4908-B62F-7110C3BF3DDB</lom:entry></lom:identifier><lom:language>en-US</lom:language><lom:metadataSchema>LOMv1.0</lom:metadataSchema></lom:metaMetadata><lom:rights><lom:copyrightAndOtherRestrictions><lom:source>LOMv1.0</lom:source><lom:value>no</lom:value></lom:copyrightAndOtherRestrictions><lom:cost><lom:source>LOMv1.0</lom:source><lom:value>no</lom:value></lom:cost></lom:rights><lom:technical><lom:format/><lom:installationRemarks><lom:string language="en-US"/></lom:installationRemarks><lom:location>http://www.eric.ed.gov/ERICWebPortal/custom/portlets/recordDetails/detailmini.jsp?_nfpb=true&amp;_&amp;ERICExtSearch_SearchValue_0=EJ563295&amp;ERICExtSearch_SearchType_0=eric_accno&amp;accno=EJ563295</lom:location><lom:otherPlatformRequirements><lom:string language="en-US"/></lom:otherPlatformRequirements><lom:size>0</lom:size></lom:technical></lom:lom>