<?xml version="1.0" encoding="UTF-8"?>
<lom:lom xmlns:lom="http://ltsc.ieee.org/xsd/LOM"><lom:educational><lom:description><lom:string language="en-US">N/A</lom:string></lom:description><lom:difficulty/><lom:intendedEndUserRole/><lom:interactivityLevel/><lom:interactivityType/><lom:learningResourceType/><lom:semanticDensity/><lom:language>en-US</lom:language></lom:educational><lom:general><lom:aggregationLevel><lom:source>LOMv1.0</lom:source><lom:value>2</lom:value></lom:aggregationLevel><lom:coverage><lom:string language="en-US">united-states</lom:string></lom:coverage><lom:description><lom:string language="en-US">Introductory treatment of crystallography, phase equilibria, and materials kinetics. Application of these principles to examples in metals, ceramics, semiconductors, and polymers, illustrating the control of structure through processing to obtain desired mechanical and physical properties. Design content includes examples and problems in materials selection and of design of materials for particular performance requirements.</lom:string></lom:description><lom:identifier><lom:catalog>NEEDS</lom:catalog><lom:entry>2470CDFE-029F-4096-A51A-864915992025</lom:entry></lom:identifier><lom:keyword><lom:string language="en-US">N/A</lom:string></lom:keyword><lom:structure><lom:source>LOMv1.0</lom:source><lom:value>hierarchical</lom:value></lom:structure><lom:title><lom:string language="en-US">Introduction to Materials Science and Engineering</lom:string></lom:title><lom:language>en-US</lom:language></lom:general><lom:lifeCycle><lom:contribute><lom:entity>BEGIN:VCARD
VERSION:3.0
SOURCE:http://www.smete.org
UID:EB32A4FF-C922-4A3D-B89B-EB6E95B7A5EB
N:Case Western Reserve University;Mark De Guire, Dept. of Materials Science and Engineering;null;;
FN:Mark De Guire, Dept. of Materials Science and Engineering Case Western Reserve University
END:vCard</lom:entity><lom:role><lom:source>LOMv1.0</lom:source><lom:value>author</lom:value></lom:role><lom:date><lom:dateTime>2007-04-01</lom:dateTime></lom:date></lom:contribute><lom:version><lom:string language="en-US">N/A</lom:string></lom:version></lom:lifeCycle><lom:metaMetadata><lom:contribute><lom:entity>BEGIN:VCARD
VERSION:3.0
SOURCE:http://www.smete.org
UID:326EC3A8-643D-4ACE-A856-9E0988B9466D
N:Kyle Criner;;;;
FN:Kyle Criner
END:vCard</lom:entity><lom:role><lom:source>LOMv1.0</lom:source><lom:value>creator</lom:value></lom:role><lom:date><lom:dateTime>2007-04-26</lom:dateTime></lom:date></lom:contribute><lom:identifier><lom:catalog>NEEDS</lom:catalog><lom:entry>2470CDFE-029F-4096-A51A-864915992025</lom:entry></lom:identifier><lom:language>en-US</lom:language><lom:metadataSchema>LOMv1.0</lom:metadataSchema></lom:metaMetadata><lom:rights><lom:copyrightAndOtherRestrictions><lom:source>LOMv1.0</lom:source><lom:value>no</lom:value></lom:copyrightAndOtherRestrictions><lom:cost><lom:source>LOMv1.0</lom:source><lom:value>no</lom:value></lom:cost></lom:rights><lom:technical><lom:format/><lom:installationRemarks><lom:string language="en-US"/></lom:installationRemarks><lom:location>http://dmseg5.case.edu/Classes/emse201/</lom:location><lom:otherPlatformRequirements><lom:string language="en-US"/></lom:otherPlatformRequirements><lom:size>0</lom:size></lom:technical></lom:lom>