<?xml version="1.0" encoding="UTF-8" standalone="no"?><Attributes><Attribute><Name>title</Name><Value>NSF ADVANCE  Program at Texas Tech</Value></Attribute><Attribute><Name>description</Name><Value>Type:  Partnerships for Adaptation, Implementation, and Dissemination;
Year Awarded: 2006. 

Description: "Texas Tech University (TTU) and Texas Tech Health Science Center (HSC) have partnered to advance the status of women faculty in engineering, science, medicine and research by addressing specific problems identified by task force studies and administrators at both institutions with "best practices" from proven ADVANCE- supported programs. These programs are being implemented in the eight departments in the College of Engineering (COE), four science departments in the College of Arts and Sciences (CAS), two departments in the School of Pharmacy (SOP), and four departments in the School of Medicine (SOM). These programs include a comprehensive recruitment plan, two mentoring programs, the third-year review, and an improved exit interview process..."</Value></Attribute><Attribute><Name>content_language</Name><Value>en-US</Value></Attribute><Attribute><Name>format</Name><Value/></Attribute><Attribute><Name>requirement</Name><Value>DEFAULT</Value></Attribute><Attribute><Name>other_platform_requirement</Name><Value/></Attribute><Attribute><Name>duration</Name><Value>DEFAULT</Value></Attribute><Attribute><Name>interactivity_type</Name><Value/></Attribute><Attribute><Name>intended_user_language</Name><Value>DEFAULT</Value></Attribute><Attribute><Name>interactivity_level</Name><Value>LOMv1.0</Value></Attribute><Attribute><Name>context</Name><Value>DEFAULT</Value></Attribute><Attribute><Name>typical_age_range_min</Name><Value>DEFAULT</Value></Attribute><Attribute><Name>typical_age_range_max</Name><Value>DEFAULT</Value></Attribute><Attribute><Name>difficulty</Name><Value>LOMv1.0</Value></Attribute><Attribute><Name>typical_learning_time</Name><Value>DEFAULT</Value></Attribute><Attribute><Name>taxon_path_concept_and_discipline</Name><Value>DEFAULT</Value></Attribute><Attribute><Name>taxon_path_skilllevel_prerequisite</Name><Value>DEFAULT</Value></Attribute><Attribute><Name>taxon_path_idea_discipline</Name><Value>DEFAULT</Value></Attribute><Attribute><Name>intended_end_user_role</Name><Value/></Attribute></Attributes>