<?xml version="1.0" encoding="UTF-8"?>
<lom:lom xmlns:lom="http://ltsc.ieee.org/xsd/LOM"><lom:educational><lom:description><lom:string language="en-US">N/A</lom:string></lom:description><lom:difficulty/><lom:intendedEndUserRole/><lom:interactivityLevel/><lom:interactivityType/><lom:learningResourceType/><lom:semanticDensity/><lom:language>en-US</lom:language></lom:educational><lom:general><lom:aggregationLevel><lom:source>LOMv1.0</lom:source><lom:value>2</lom:value></lom:aggregationLevel><lom:coverage><lom:string language="en-US">united-states</lom:string></lom:coverage><lom:description><lom:string language="en-US">The tr660 program models the mineralogy and physical properties for various chemical compositions in the Earth's mantle where a transition occurs in these properties at about 660 km depth. The program is based on the algorithm described in a paper by Donald J. Weidner and Yanbin Wang. It is written in Java from a FORTRAN code originally developed for this paper. This program is designed to be used for research purposed to test the effects of varying chemical composition, temperature, and physical properties on the inferred physical properties of the Earth through these phase transformations. The graphing output is versatile allowing the user to view any of the calculated variables as a function of depth. The output can be imported to a file in the users platform for further analysis.</lom:string></lom:description><lom:identifier><lom:catalog>NEEDS</lom:catalog><lom:entry>284C69CB-7C7F-41AA-B5D7-D9991DE74BAA</lom:entry></lom:identifier><lom:keyword><lom:string language="en-US">Geophysics,Mineralogy or petrology</lom:string></lom:keyword><lom:structure><lom:source>LOMv1.0</lom:source><lom:value>hierarchical</lom:value></lom:structure><lom:title><lom:string language="en-US">The tr660 Program</lom:string></lom:title><lom:language>en-US</lom:language></lom:general><lom:lifeCycle><lom:contribute><lom:entity>BEGIN:VCARD
VERSION:3.0
SOURCE:http://www.smete.org
UID:BBC1F313-03B3-41D0-A563-396EB5024F16
N:Nuzzi;Eric;;;
FN:Eric  Nuzzi
TITLE:Mr
ORG:State University New York, Stony Brook
END:vCard</lom:entity><lom:role><lom:source>LOMv1.0</lom:source><lom:value>author</lom:value></lom:role><lom:date><lom:dateTime>2001-03-01</lom:dateTime></lom:date></lom:contribute><lom:contribute><lom:entity>BEGIN:VCARD
VERSION:3.0
SOURCE:http://www.smete.org
UID:CA001C50-77CA-43DC-A761-95207D386EDD
N:Digital Library for Earth System Education;;;;
FN:Digital Library for Earth System Education
ADR;TYPE=work,postal,parcel:;;UCAR/DPC, PO Box 3000;Boulder;CO;80307-3000;
TEL;TYPE=work,voice:1-303-497-2656
TEL;TYPE=work,fax:1-303-497-8336
PHOTO;VALUE=uri:http://www.smete.org/images/affiliation/dlese.gif
URL:http://www.dlese.org/
END:vCard</lom:entity><lom:role><lom:source>LOMv1.0</lom:source><lom:value>publisher</lom:value></lom:role><lom:date><lom:dateTime>2001-03-01</lom:dateTime></lom:date></lom:contribute><lom:version><lom:string language="en-US">N/A</lom:string></lom:version></lom:lifeCycle><lom:metaMetadata><lom:contribute><lom:entity>BEGIN:VCARD
VERSION:3.0
SOURCE:http://www.smete.org
UID:710FE693-46E9-4002-BA94-1BE2E6218CD6
N:Andy Dong;;;;
FN:Andy Dong
TEL;TYPE=work,voice:5106431819
TEL;TYPE=work,fax:5106431822
END:vCard</lom:entity><lom:role><lom:source>LOMv1.0</lom:source><lom:value>creator</lom:value></lom:role><lom:date><lom:dateTime>2002-05-28</lom:dateTime></lom:date></lom:contribute><lom:identifier><lom:catalog>NEEDS</lom:catalog><lom:entry>284C69CB-7C7F-41AA-B5D7-D9991DE74BAA</lom:entry></lom:identifier><lom:language>en-US</lom:language><lom:metadataSchema>LOMv1.0</lom:metadataSchema></lom:metaMetadata><lom:rights><lom:copyrightAndOtherRestrictions><lom:source>LOMv1.0</lom:source><lom:value>no</lom:value></lom:copyrightAndOtherRestrictions><lom:cost><lom:source>LOMv1.0</lom:source><lom:value>no</lom:value></lom:cost></lom:rights><lom:technical><lom:format/><lom:installationRemarks><lom:string language="en-US">N/A</lom:string></lom:installationRemarks><lom:location>http://www.journey.sunysb.edu/ProjectJava/tr660/home.html</lom:location><lom:otherPlatformRequirements><lom:string language="en-US">N/A</lom:string></lom:otherPlatformRequirements><lom:size>0</lom:size></lom:technical></lom:lom>