<?xml version="1.0" encoding="UTF-8" standalone="no"?><Attributes><Attribute><Name>title</Name><Value>Nanoworld's Organization of Nanotechnology</Value></Attribute><Attribute><Name>description</Name><Value>"Underlying the Nanoworlds Learning Resource is Nanopedia, The Web Encyclopedia of Nanotechnology. On the one hand, Nanoworlds provides learning modules for formal education; on the other, Nanopedia is a searchable knowledge base.

You are now located at the entry point, or root, of Nanopedia. From here, it branches out in four directions: the science of the Nanoscale, Nanoengineering, the impact of nanotechnology on Society and Applications, and the Future of Nanotechnology as depicted in art, fiction and earnest speculation."
There is an overview and then links to four main topics areas: nanoscience, nanoengineering, impacts and applications and futurism, fiction and art."

Site map: Site Map. Aside from special paths and formal course support, Nanopedia is a heirarchical, as opposed to alphabetical, knowledge base.</Value></Attribute><Attribute><Name>content_language</Name><Value>en-US</Value></Attribute><Attribute><Name>format</Name><Value/></Attribute><Attribute><Name>requirement</Name><Value>DEFAULT</Value></Attribute><Attribute><Name>other_platform_requirement</Name><Value/></Attribute><Attribute><Name>duration</Name><Value>DEFAULT</Value></Attribute><Attribute><Name>interactivity_type</Name><Value/></Attribute><Attribute><Name>intended_user_language</Name><Value>DEFAULT</Value></Attribute><Attribute><Name>interactivity_level</Name><Value>LOMv1.0</Value></Attribute><Attribute><Name>context</Name><Value>DEFAULT</Value></Attribute><Attribute><Name>typical_age_range_min</Name><Value>DEFAULT</Value></Attribute><Attribute><Name>typical_age_range_max</Name><Value>DEFAULT</Value></Attribute><Attribute><Name>difficulty</Name><Value>LOMv1.0</Value></Attribute><Attribute><Name>typical_learning_time</Name><Value>DEFAULT</Value></Attribute><Attribute><Name>taxon_path_concept_and_discipline</Name><Value>DEFAULT</Value></Attribute><Attribute><Name>taxon_path_skilllevel_prerequisite</Name><Value>DEFAULT</Value></Attribute><Attribute><Name>taxon_path_idea_discipline</Name><Value>DEFAULT</Value></Attribute><Attribute><Name>intended_end_user_role</Name><Value/></Attribute></Attributes>